[
  {
    "name": "# Announcements",
    "eTag": "AbOx6N+6vu3zoAE",
    "id": "space.149e70f311739f2a7c6515f7b34",
    "updated": "2020-09-23T09:23:37.175764Z"
  },
  {
    "name": "# Rules",
    "eTag": "AbOx6N+6vu3zoAE",
    "id": "space.149e70f311749f2a7c6515f7b34",
    "updated": "2020-09-23T09:23:37.175764Z"
  },
  {
    "name": "# Music",
    "eTag": "AbOx6N+6vu3zoAE",
    "id": "space.149e60f311749f2a7c6515f7b34",
    "updated": "2020-09-23T09:23:37.175764Z"
  },
  {
    "name": "# Travel",
    "eTag": "Ab+2+deSmdf/Fw",
    "id": "space.2ada61db17878cd388f95da34f9",
    "updated": "2020-09-23T09:23:36.960491Z"
  },
  {
    "name": "# Crypto",
    "eTag": "AcrWgrqgmcyHswE",
    "id": "space.363d9255193e45f190539e0c7d5",
    "updated": "2020-09-23T09:23:37.183458Z"
  },
  {
    "name": "# Sports",
    "eTag": "AZSu2tPUuLeO2QE",
    "id": "space.515fc9a2a1a895f4059c84b2971",
    "updated": "2020-09-23T09:23:36.935077Z"
  },
  {
    "name": "# NFTMania baby",
    "eTag": "AZ2/xY3Qv9GGUQ",
    "id": "space.a204f87d215a40985d35cf84bf5",
    "updated": "2020-09-23T09:23:36.945993Z"
  },
  {
    "name": "# Music for cryptos",
    "eTag": "AfD93cn945yNTA",
    "id": "space.a652eb6cc340334ff0b244c4a39",
    "updated": "2020-09-23T09:23:36.951506Z"
  },
  {
    "name": "# NFTMania baby",
    "eTag": "AfeD+Zn+idGFTQ",
    "id": "space.ac4e67b98b34b44c4a39466e93e",
    "updated": "2021-02-19T18:01:51.886025Z"
  },
  {
    "name": "# Music for cryptos",
    "eTag": "Adzu4uSC45jGsgE",
    "id": "space.c1ee1eda28554d0a34f9b9df5cfe",
    "updated": "2020-09-23T09:23:36.939098Z"
  },
  {
    "name": "# NFTMania baby",
    "eTag": "AYTS0uL/zs/nXA",
    "id": "space.ce466f2e445c38976168ba78e46",
    "updated": "2020-09-23T09:23:37.170896Z"
  },
  {
    "name": "# Music for cryptos",
    "eTag": "Ade5g4XZzN652AE",
    "id": "space.e1eda2fd92e551358e4af1b6174",
    "updated": "2020-09-23T09:23:37.18019Z"
  }
]